elastiknn/__init__.py
elastiknn/api.py
elastiknn/client.py
elastiknn/codec.py
elastiknn/models.py
elastiknn/utils.py
elastiknn_client-8.15.3.0.dist-info/METADATA
elastiknn_client-8.15.3.0.dist-info/WHEEL
elastiknn_client-8.15.3.0.dist-info/top_level.txt
elastiknn_client-8.15.3.0.dist-info/RECORD
