Metadata-Version: 2.1
Name: elastiknn-client
Version: 8.15.3.0
Summary: Python client for the ElastiKnn Elasticsearch plugin
Home-page: https://github.com/alexklibisz/elastiknn
Author: Alex Klibisz
Author-email: aklibisz@gmail.com
Requires-Dist: elasticsearch==8.14.0
Requires-Dist: tqdm==4.61.1
Requires-Dist: scipy==1.10.1
